eb2csv/__init__.py
eb2csv/eb2csv.py
eb2csv/fieldconfig.py
eb2csv-0.1.3.dist-info/DESCRIPTION.rst
eb2csv-0.1.3.dist-info/METADATA
eb2csv-0.1.3.dist-info/RECORD
eb2csv-0.1.3.dist-info/WHEEL
eb2csv-0.1.3.dist-info/entry_points.txt
eb2csv-0.1.3.dist-info/metadata.json
eb2csv-0.1.3.dist-info/top_level.txt
