Metadata-Version: 2.0
Name: eb2csv
Version: 0.1.3
Summary: A Python (3.6) CLI tool for recording measurement data from Gildemeister Energy Box data loggers into csv files.
Home-page: https://bitbucket.org/gildemeisterenergyefficiency/eb2csv/
Author: GILDEMEISTER energy efficiency GmbH
Author-email: energyefficiency@gildemeister.com
License: MIT
Platform: UNKNOWN
Classifier: Programming Language :: Python
Classifier: Programming Language :: Python :: 3.6
Classifier: License :: OSI Approved :: MIT License
Classifier: Operating System :: OS Independent
Requires-Python: >=3.6
Requires-Dist: click
Requires-Dist: arrow
Requires-Dist: requests
